verify_version_spec
